{
  "url": "https://www.telesurtv.net/venezuela-asegura-que-produccion-petrolera-se-mantiene-pese-a-escalada-violenta-de-ee-uu/",
  "title": "Venezuela asegura que producción petrolera se mantiene pese a escalada violenta de EE.UU. - teleSUR",
  "section": "América Latina y El Caribe",
  "tags": [
    "Delcy Rodríguez",
    "EE.UU.",
    "Prducción petrolera",
    "Venezuela"
  ],
  "text": "\nLa vicepresidenta de Venezuela, Delcy Rodríguez, aseguró este jueves que el país continúa en firme con la producción de petróleo y de gas, una recuperación que se ha logrado con esfuerzo propio y pese a la escalada violenta de Estados Unidos (EE.UU.) contra todo el mundo.\n“La producción petrolera y de gas de Venezuela se mantienen y en proceso de recuperación con esfuerzo propio, que es el camino que debe guiarnos (…) es la única conducción posible para salir victoriosos y airosos de esta escalada violenta contra toda la humanidad”, indicó la funcionaria en un discurso emitido en la Asamblea Nacional, donde entregó el Decreto de Emergencia Económica, dictado y firmado por el presidente Nicolás Maduro.\nRodríguez resaltó cómo el presidente de Estados Unidos, Donald Trump, primero impuso aranceles a todo el mundo, y después decretó una tregua de tres meses, excepto a China, país al que le ha aplicado aranceles superiores al 120 por ciento.\nLa vicemandataria venezolana mencionó que la política arancelaria de Trump es el inicio “de una guerra comercial contra todos los bloques de países del mundo, es el inicio de una escalada violenta para una reconfiguración, donde Estados Unidos pretende ser el dueño del mundo”.\nNo obstante, puntualizó que el principal afectado por esta guerra arancelaria es el mismo pueblo norteamericano, es el que sufre las consecuencias de las acciones gestadas por su Gobierno.\nRodríguez señaló que el presidente Maduro ha rechazado las restricciones impuestas por EE.UU. sobre a quién se le puede vender petróleo, y ha dejado claro que “el mundo entero es el mercado para Venezuela”.\n“Vamos a trabajar con las empresas que nos parezcan adecuadas, en función de los intereses nacionales”, externó y agregó que se invitó a las empresas transnacionales a trabajar en el país “conforme a nuestras leyes y respetando también el Derecho Internacional”.\nAl abordar el bloqueo criminal que Estados Unidos ejerce sobre Venezuela, la vicepresidenta dijo que detrás de todas las medidas contra el país está la extrema derecha venezolana.\nMencionó un incidente protagonizado por la congresista estadounidense María Elvira Salazar, quien clamó por acciones que afectarían directamente las operaciones de la empresa petrolera Chevron en el país.\n‘’Gritaba que ella haría lo que la Machado le pidiera desde Venezuela, que si la Machado le pedía quitar licencias, había que quitarle la licencia a Chevron, y le decía inmoral a Chevron por trabajar en Venezuela’’, anotó la vicepresidenta, recordando que la transnacional “tiene más de un siglo trabajando” en esta nación suramericana.\n",
  "source_metadata": {
    "url": "https://www.telesurtv.net/venezuela-asegura-que-produccion-petrolera-se-mantiene-pese-a-escalada-violenta-de-ee-uu/",
    "json_file": "Data/teleSUR_tv/2025/mensajes_teleSUR_tv_2025-04.json",
    "message_index": 1299,
    "message_id": 91618,
    "date": "2025-04-11T09:55:12+00:00",
    "text": "teleSUR\nVenezuela asegura que producción petrolera se mantiene pese a escalada violenta de EE.UU.\nhttps://www.telesurtv.net/venezuela-asegura-que-produccion-petrolera-se-mantiene-pese-a-escalada-violenta-de-ee-uu/",
    "photo_path": null,
    "views": 2070,
    "reactions": {
      "👍": 44,
      "👏": 14
    },
    "total_reactions": 58
  },
  "preprocessing": {
    "cleaned": "la vicepresidenta de venezuela, delcy rodríguez, aseguró este jueves que el país continúa en firme con la producción de petróleo y de gas, una recuperación que se ha logrado con esfuerzo propio y pese a la escalada violenta de estados unidos (ee.uu.) contra todo el mundo. “la producción petrolera y de gas de venezuela se mantienen y en proceso de recuperación con esfuerzo propio, que es el camino que debe guiarnos (…) es la única conducción posible para salir victoriosos y airosos de esta escalada violenta contra toda la humanidad”, indicó la funcionaria en un discurso emitido en la asamblea nacional, donde entregó el decreto de emergencia económica, dictado y firmado por el presidente nicolás maduro. rodríguez resaltó cómo el presidente de estados unidos, donald trump, primero impuso aranceles a todo el mundo, y después decretó una tregua de tres meses, excepto a china, país al que le ha aplicado aranceles superiores al 120 por ciento. la vicemandataria venezolana mencionó que la política arancelaria de trump es el inicio “de una guerra comercial contra todos los bloques de países del mundo, es el inicio de una escalada violenta para una reconfiguración, donde estados unidos pretende ser el dueño del mundo”. no obstante, puntualizó que el principal afectado por esta guerra arancelaria es el mismo pueblo norteamericano, es el que sufre las consecuencias de las acciones gestadas por su gobierno. rodríguez señaló que el presidente maduro ha rechazado las restricciones impuestas por ee.uu. sobre a quién se le puede vender petróleo, y ha dejado claro que “el mundo entero es el mercado para venezuela”. “vamos a trabajar con las empresas que nos parezcan adecuadas, en función de los intereses nacionales”, externó y agregó que se invitó a las empresas transnacionales a trabajar en el país “conforme a nuestras leyes y respetando también el derecho internacional”. al abordar el bloqueo criminal que estados unidos ejerce sobre venezuela, la vicepresidenta dijo que detrás de todas las medidas contra el país está la extrema derecha venezolana. mencionó un incidente protagonizado por la congresista estadounidense maría elvira salazar, quien clamó por acciones que afectarían directamente las operaciones de la empresa petrolera chevron en el país. ‘’gritaba que ella haría lo que la machado le pidiera desde venezuela, que si la machado le pedía quitar licencias, había que quitarle la licencia a chevron, y le decía inmoral a chevron por trabajar en venezuela’’, anotó la vicepresidenta, recordando que la transnacional “tiene más de un siglo trabajando” en esta nación suramericana.",
    "tokens": [
      "vicepresidenta",
      "venezuela",
      ",",
      "delcy",
      "rodríguez",
      ",",
      "aseguró",
      "jueves",
      "país",
      "continúa",
      "firme",
      "producción",
      "petróleo",
      "gas",
      ",",
      "recuperación",
      "logrado",
      "esfuerzo",
      "propio",
      "pese",
      "escalada",
      "violenta",
      "unidos",
      "(",
      "ee.uu.",
      ")",
      "mundo",
      ".",
      "“",
      "producción",
      "petrolera",
      "gas",
      "venezuela",
      "mantienen",
      "proceso",
      "recuperación",
      "esfuerzo",
      "propio",
      ",",
      "camino",
      "debe",
      "guiarnos",
      "(",
      "…",
      ")",
      "única",
      "conducción",
      "posible",
      "salir",
      "victoriosos",
      "airosos",
      "escalada",
      "violenta",
      "toda",
      "humanidad",
      "”",
      ",",
      "indicó",
      "funcionaria",
      "discurso",
      "emitido",
      "asamblea",
      "nacional",
      ",",
      "entregó",
      "decreto",
      "emergencia",
      "económica",
      ",",
      "dictado",
      "firmado",
      "presidente",
      "nicolás",
      "maduro",
      ".",
      "rodríguez",
      "resaltó",
      "cómo",
      "presidente",
      "unidos",
      ",",
      "donald",
      "trump",
      ",",
      "primero",
      "impuso",
      "aranceles",
      "mundo",
      ",",
      "después",
      "decretó",
      "tregua",
      "tres",
      "meses",
      ",",
      "excepto",
      "china",
      ",",
      "país",
      "aplicado",
      "aranceles",
      "superiores",
      "120",
      "ciento",
      ".",
      "vicemandataria",
      "venezolana",
      "mencionó",
      "política",
      "arancelaria",
      "trump",
      "inicio",
      "“",
      "guerra",
      "comercial",
      "bloques",
      "países",
      "mundo",
      ",",
      "inicio",
      "escalada",
      "violenta",
      "reconfiguración",
      ",",
      "unidos",
      "pretende",
      "ser",
      "dueño",
      "mundo",
      "”",
      ".",
      "obstante",
      ",",
      "puntualizó",
      "principal",
      "afectado",
      "guerra",
      "arancelaria",
      "mismo",
      "pueblo",
      "norteamericano",
      ",",
      "sufre",
      "consecuencias",
      "acciones",
      "gestadas",
      "gobierno",
      ".",
      "rodríguez",
      "señaló",
      "presidente",
      "maduro",
      "rechazado",
      "restricciones",
      "impuestas",
      "ee.uu.",
      "quién",
      "puede",
      "vender",
      "petróleo",
      ",",
      "dejado",
      "claro",
      "“",
      "mundo",
      "entero",
      "mercado",
      "venezuela",
      "”",
      ".",
      "“",
      "vamos",
      "trabajar",
      "empresas",
      "parezcan",
      "adecuadas",
      ",",
      "función",
      "intereses",
      "nacionales",
      "”",
      ",",
      "externó",
      "agregó",
      "invitó",
      "empresas",
      "transnacionales",
      "trabajar",
      "país",
      "“",
      "conforme",
      "leyes",
      "respetando",
      "derecho",
      "internacional",
      "”",
      ".",
      "abordar",
      "bloqueo",
      "criminal",
      "unidos",
      "ejerce",
      "venezuela",
      ",",
      "vicepresidenta",
      "dijo",
      "detrás",
      "todas",
      "medidas",
      "país",
      "extrema",
      "derecha",
      "venezolana",
      ".",
      "mencionó",
      "incidente",
      "protagonizado",
      "congresista",
      "estadounidense",
      "maría",
      "elvira",
      "salazar",
      ",",
      "clamó",
      "acciones",
      "afectarían",
      "directamente",
      "operaciones",
      "empresa",
      "petrolera",
      "chevron",
      "país",
      ".",
      "‘",
      "’",
      "gritaba",
      "haría",
      "machado",
      "pidiera",
      "venezuela",
      ",",
      "si",
      "machado",
      "pedía",
      "quitar",
      "licencias",
      ",",
      "quitarle",
      "licencia",
      "chevron",
      ",",
      "decía",
      "inmoral",
      "chevron",
      "trabajar",
      "venezuela",
      "’",
      "’",
      ",",
      "anotó",
      "vicepresidenta",
      ",",
      "recordando",
      "transnacional",
      "“",
      "siglo",
      "trabajando",
      "”",
      "nación",
      "suramericana",
      "."
    ],
    "token_count": 271,
    "sentence_count": 10
  },
  "pos_analysis": {
    "tag_freq": {
      "NNP": 52,
      "FW": 64,
      "VBZ": 7,
      "NN": 177,
      "NNS": 21,
      "VBP": 17,
      "JJ": 38,
      "IN": 13,
      "CD": 1,
      "CC": 1,
      "VBD": 1
    },
    "bigram_freq": {
      "NNP-FW": 6,
      "FW-FW": 30,
      "FW-NNP": 9,
      "NNP-NNP": 19,
      "NNP-VBZ": 6,
      "VBZ-NN": 2,
      "NN-NNS": 11,
      "NNS-VBP": 17,
      "VBP-JJ": 10,
      "JJ-NN": 29,
      "NN-NN": 105,
      "NN-IN": 12,
      "IN-JJ": 5,
      "NN-FW": 17,
      "FW-NN": 20,
      "NN-JJ": 10,
      "JJ-FW": 1,
      "NNP-JJ": 2,
      "NN-NNP": 19,
      "IN-NN": 1,
      "VBP-NN": 1,
      "NNP-NN": 18,
      "IN-FW": 6,
      "FW-JJ": 2,
      "JJ-NNP": 3,
      "VBZ-JJ": 2,
      "IN-NNS": 1,
      "NNS-NNS": 2,
      "VBP-NNP": 1,
      "NN-VBZ": 1,
      "VBZ-NNS": 1,
      "VBP-CD": 1,
      "CD-NN": 1,
      "NNP-CC": 1,
      "CC-JJ": 1,
      "JJ-JJ": 5,
      "VBP-NNS": 3,
      "NNS-FW": 2,
      "FW-NNS": 3,
      "VBP-IN": 1,
      "NN-VBD": 1,
      "VBD-JJ": 1,
      "VBZ-FW": 2
    },
    "trigram_freq": {
      "NNP-FW-FW": 1,
      "FW-FW-NNP": 3,
      "FW-NNP-NNP": 5,
      "NNP-NNP-NNP": 7,
      "NNP-NNP-VBZ": 2,
      "NNP-VBZ-NN": 2,
      "VBZ-NN-NNS": 1,
      "NN-NNS-VBP": 10,
      "NNS-VBP-JJ": 10,
      "VBP-JJ-NN": 8,
      "JJ-NN-NN": 18,
      "NN-NN-IN": 7,
      "NN-IN-JJ": 5,
      "IN-JJ-NN": 2,
      "NN-NN-FW": 10,
      "NN-FW-FW": 5,
      "FW-FW-FW": 19,
      "FW-FW-NN": 7,
      "FW-NN-JJ": 2,
      "NN-JJ-NN": 8,
      "NN-NN-NN": 61,
      "NN-NN-JJ": 7,
      "IN-JJ-FW": 1,
      "JJ-FW-FW": 1,
      "NNP-NNP-JJ": 1,
      "NNP-JJ-NN": 2,
      "JJ-NN-FW": 2,
      "NN-FW-NN": 7,
      "FW-NN-NNP": 4,
      "NN-NNP-FW": 2,
      "NNP-FW-NN": 4,
      "FW-NN-IN": 2,
      "NN-IN-NN": 1,
      "IN-NN-FW": 1,
      "NN-FW-NNP": 4,
      "FW-NNP-FW": 1,
      "FW-NN-FW": 4,
      "FW-NN-NN": 7,
      "NN-NN-NNS": 6,
      "NNS-VBP-NN": 1,
      "VBP-NN-NNP": 1,
      "NN-NNP-NN": 5,
      "NNP-NN-JJ": 1,
      "NN-IN-FW": 5,
      "IN-FW-FW": 2,
      "FW-FW-JJ": 1,
      "FW-JJ-NN": 2,
      "IN-FW-NNP": 1,
      "NNP-NNP-NN": 8,
      "NNP-NN-NN": 17,
      "NN-JJ-NNP": 2,
      "JJ-NNP-FW": 1,
      "NNP-FW-NNP": 1,
      "NNP-VBZ-JJ": 2,
      "VBZ-JJ-NN": 2,
      "NN-NN-NNP": 12,
      "NN-NNP-NNP": 7,
      "JJ-NN-IN": 3,
      "NN-IN-NNS": 1,
      "IN-NNS-NNS": 1,
      "NNS-NNS-VBP": 2,
      "NNS-VBP-NNP": 1,
      "VBP-NNP-NN": 1,
      "NN-NN-VBZ": 1,
      "NN-VBZ-NNS": 1,
      "VBZ-NNS-VBP": 1,
      "NNS-VBP-CD": 1,
      "VBP-CD-NN": 1,
      "CD-NN-NN": 1,
      "FW-NNP-CC": 1,
      "NNP-CC-JJ": 1,
      "CC-JJ-NN": 1,
      "IN-JJ-JJ": 2,
      "JJ-JJ-JJ": 2,
      "JJ-JJ-NN": 3,
      "JJ-NN-NNS": 3,
      "NNS-VBP-NNS": 3,
      "VBP-NNS-VBP": 2,
      "VBP-NNS-FW": 1,
      "NNS-FW-FW": 2,
      "NNP-NNP-FW": 1,
      "IN-FW-NNS": 3,
      "FW-NNS-VBP": 2,
      "JJ-NN-NNP": 2,
      "VBP-JJ-NNP": 1,
      "JJ-NNP-NN": 2,
      "VBP-JJ-JJ": 1,
      "FW-NNS-NNS": 1,
      "NNS-VBP-IN": 1,
      "VBP-IN-FW": 1,
      "FW-NN-NNS": 1,
      "NN-NN-VBD": 1,
      "NN-VBD-JJ": 1,
      "VBD-JJ-NN": 1,
      "NN-NNP-VBZ": 4,
      "NNP-VBZ-FW": 2,
      "VBZ-FW-NN": 2,
      "NN-NNP-JJ": 1,
      "NN-NNS-FW": 1,
      "VBZ-NN-NN": 1,
      "FW-NNP-NN": 2,
      "NN-FW-JJ": 1
    },
    "top_patterns": {
      "top_tags": {
        "NN": 177,
        "FW": 64,
        "NNP": 52,
        "JJ": 38,
        "NNS": 21
      },
      "top_bigrams": {
        "NN-NN": 105,
        "FW-FW": 30,
        "JJ-NN": 29,
        "FW-NN": 20,
        "NNP-NNP": 19
      },
      "top_trigrams": {
        "NN-NN-NN": 61,
        "FW-FW-FW": 19,
        "JJ-NN-NN": 18,
        "NNP-NN-NN": 17,
        "NN-NN-NNP": 12
      }
    }
  },
  "grammar_analysis": {
    "sentence_count": 10,
    "chunk_counts": {
      "NP": 105,
      "VP": 29,
      "PP": 5,
      "ADJP": 2
    },
    "top_rules": [
      {
        "rule": "PP -> ('de', 'IN') NP",
        "frequency": 4,
        "weight": 0.0265
      },
      {
        "rule": "NP -> ('La', 'NNP')",
        "frequency": 2,
        "weight": 0.0132
      },
      {
        "rule": "NP -> ('Venezuela', 'NNP')",
        "frequency": 2,
        "weight": 0.0132
      },
      {
        "rule": "VP -> ('que', 'VBP') NP",
        "frequency": 2,
        "weight": 0.0132
      },
      {
        "rule": "NP -> ('gas', 'NN')",
        "frequency": 2,
        "weight": 0.0132
      },
      {
        "rule": "NP -> ('Estados', 'NNP') ('Unidos', 'NNP')",
        "frequency": 2,
        "weight": 0.0132
      },
      {
        "rule": "NP -> ('mundo', 'NN')",
        "frequency": 2,
        "weight": 0.0132
      },
      {
        "rule": "VP -> ('aranceles', 'VBZ') NP",
        "frequency": 2,
        "weight": 0.0132
      },
      {
        "rule": "VP -> ('le', 'VBZ') NP",
        "frequency": 2,
        "weight": 0.0132
      },
      {
        "rule": "S -> NP ('vicepresidenta', 'FW') ('de', 'FW') NP (',', ',') NP (',', ',') NP VP PP ('producción', 'FW') ('de', 'FW') ('petróleo', 'FW') ('y', 'FW') ('de', 'FW') NP (',', ',') NP NP VP VP ('escalada', 'FW') ('violenta', 'FW') ('de', 'FW') NP ('(', '(') NP (')', ')') VP ('el', 'FW') NP ('.', '.')",
        "frequency": 1,
        "weight": 0.0066
      }
    ],
    "sample_chunks": [
      {
        "label": "NP",
        "text": "La"
      },
      {
        "label": "NP",
        "text": "Venezuela"
      },
      {
        "label": "NP",
        "text": "Delcy Rodríguez"
      },
      {
        "label": "NP",
        "text": "aseguró este jueves"
      },
      {
        "label": "VP",
        "text": "que el país continúa"
      },
      {
        "label": "NP",
        "text": "el país continúa"
      },
      {
        "label": "PP",
        "text": "en firme con la"
      },
      {
        "label": "NP",
        "text": "firme con la"
      },
      {
        "label": "NP",
        "text": "gas"
      },
      {
        "label": "NP",
        "text": "una recuperación que se ha"
      },
      {
        "label": "NP",
        "text": "logrado con esfuerzo propio"
      },
      {
        "label": "VP",
        "text": "y"
      },
      {
        "label": "VP",
        "text": "pese a la"
      },
      {
        "label": "NP",
        "text": "a la"
      },
      {
        "label": "NP",
        "text": "Estados Unidos"
      }
    ],
    "clause_structures": [
      "(S\n  (NP La/NNP)\n  vicepresidenta/FW\n  de/FW\n  (NP Venezuela/NNP)\n  ,/,\n  (NP Delcy/NNP Rodríguez/NNP)\n  ,/,\n  (NP aseguró/JJ este/NN jueves/NNS)\n  (VP que/VBP (NP el/JJ país/NN continúa/NN))\n  (PP en/IN (NP firme/JJ con/NN la/NN))\n  producción/FW\n  de/FW\n  petróleo/FW\n  y/FW\n  de/FW\n  (NP gas/NN)\n  ,/,\n  (NP una/JJ recuperación/NN que/NN se/NN ha/NN)\n  (NP logrado/JJ con/NN esfuerzo/NN propio/NN)\n  (VP y/VBZ)\n  (VP pese/VBZ (NP a/DT la/NN))\n  escalada/FW\n  violenta/FW\n  de/FW\n  (NP Estados/NNP Unidos/NNP)\n  (/(\n  (NP EE.UU./NNP)\n  )/)\n  (VP contra/VBP todo/JJ)\n  el/FW\n  (NP mundo/NN)\n  ./.)",
      "(S\n  (NP “/JJ La/NNP producción/NN petrolera/NN y/NN)\n  (PP de/IN (NP gas/NN))\n  de/FW\n  (NP Venezuela/NNP)\n  se/FW\n  (NP mantienen/NN y/NN)\n  en/FW\n  proceso/FW\n  de/FW\n  recuperación/FW\n  (NP con/NN esfuerzo/NN propio/NN)\n  ,/,\n  (NP que/JJ es/NN el/NN camino/NN que/NN debe/NN guiarnos/NN)\n  (/(\n  (NP …/NNP)\n  )/)\n  (VP\n    es/VBP\n    (NP la/NN única/NNP conducción/NN)\n    (NP posible/JJ para/NN salir/NN victoriosos/NN y/NN airosos/NN))\n  de/IN\n  esta/FW\n  escalada/FW\n  violenta/FW\n  contra/FW\n  (NP toda/NN)\n  la/FW\n  (NP humanidad/NN ”/NN)\n  ,/,\n  (ADJP indicó/JJ)\n  la/FW\n  funcionaria/FW\n  en/FW\n  (NP un/JJ discurso/NN emitido/NN)\n  en/IN\n  la/FW\n  (NP Asamblea/NNP Nacional/NNP)\n  ,/,\n  (NP donde/NN entregó/NN)\n  (NP el/JJ Decreto/NNP)\n  de/FW\n  (NP Emergencia/NNP Económica/NNP)\n  ,/,\n  (NP\n    dictado/NN\n    y/NN\n    firmado/NN\n    por/NN\n    el/NN\n    presidente/NN\n    Nicolás/NNP\n    Maduro/NNP)\n  ./.)",
      "(S\n  (NP Rodríguez/NNP resaltó/NN cómo/NN)\n  el/FW\n  (NP presidente/NN)\n  de/FW\n  (NP Estados/NNP Unidos/NNP)\n  ,/,\n  (NP Donald/NNP Trump/NNP)\n  ,/,\n  (NP primero/NN impuso/NN)\n  (VP aranceles/VBZ (NP a/DT todo/NN el/NN mundo/NN))\n  ,/,\n  y/CC\n  (NP después/JJ decretó/NN)\n  (NP una/JJ tregua/NN)\n  (PP de/IN (NP tres/NNS meses/NNS))\n  ,/,\n  (VP excepto/VBP (NP a/DT China/NNP))\n  ,/,\n  (NP país/NN al/NN que/NN le/NN ha/NN aplicado/NN)\n  (VP aranceles/VBZ (NP superiores/NNS))\n  (VP al/VBP)\n  120/CD\n  (NP por/NN ciento/NN)\n  ./.)",
      "(S\n  (NP La/NNP)\n  vicemandataria/FW\n  (NP venezolana/NN mencionó/NN que/NN la/NN)\n  política/FW\n  arancelaria/FW\n  de/FW\n  (NP Trump/NNP)\n  es/CC\n  (NP el/JJ inicio/JJ “/NN)\n  (PP de/IN (NP una/JJ guerra/JJ comercial/JJ contra/NN todos/NNS))\n  (VP los/VBP (NP bloques/NNS))\n  (VP de/VBP (NP países/NNS))\n  del/FW\n  (NP mundo/NN)\n  ,/,\n  (ADJP es/JJ)\n  el/FW\n  inicio/FW\n  de/FW\n  una/FW\n  escalada/FW\n  violenta/FW\n  (NP para/NN)\n  (NP una/JJ reconfiguración/NN)\n  ,/,\n  (NP donde/JJ Estados/NNP Unidos/NNP)\n  pretende/FW\n  (NP ser/NN el/NN dueño/NN)\n  del/FW\n  (NP mundo/NN ”/NN)\n  ./.)",
      "(S\n  (NP No/DT obstante/NN)\n  ,/,\n  (NP puntualizó/NN que/NN el/NN)\n  (NP principal/JJ afectado/NN por/NN)\n  (NP esta/JJ guerra/NN arancelaria/NNS)\n  (VP es/VBP (NP el/JJ mismo/NN pueblo/NN norteamericano/NN))\n  ,/,\n  (NP es/JJ el/NN que/NN sufre/NN)\n  (NP las/JJ consecuencias/NN)\n  de/IN\n  las/FW\n  (NP acciones/NNS)\n  (VP gestadas/VBP (NP por/JJ su/NN Gobierno/NNP))\n  ./.)"
    ]
  },
  "regex_annotations": {
    "categories": [
      "GOBIERNOS_OFICIALES",
      "GRUPOS_ESPECIFICOS",
      "ELECCIONES_PROCESOS_POLITICOS",
      "ANTIIMPERIALISMO_SOBERANIA",
      "PAISES",
      "ECONOMIA_COMERCIO_FINANZAS",
      "CONFLICTOS_ARMADOS_OPERACIONES"
    ],
    "matches": [
      {
        "category": "CONFLICTOS_ARMADOS_OPERACIONES",
        "matched_text": "guerra comercial contra todos",
        "position": [
          1048,
          1077
        ],
        "start": 1048,
        "end": 1077
      },
      {
        "category": "ECONOMIA_COMERCIO_FINANZAS",
        "matched_text": "guerra comercial contra todos los bloques de países del mundo, es el inicio de una escalada violenta para una reconfiguración, donde estados unidos",
        "position": [
          1048,
          1195
        ],
        "start": 1048,
        "end": 1195
      },
      {
        "category": "ELECCIONES_PROCESOS_POLITICOS",
        "matched_text": "discurso emitido en la asamblea nacional",
        "position": [
          568,
          608
        ],
        "start": 568,
        "end": 608
      },
      {
        "category": "ELECCIONES_PROCESOS_POLITICOS",
        "matched_text": "señaló",
        "position": [
          1429,
          1435
        ],
        "start": 1429,
        "end": 1435
      },
      {
        "category": "GOBIERNOS_OFICIALES",
        "matched_text": "presidente nicolás maduro",
        "position": [
          685,
          710
        ],
        "start": 685,
        "end": 710
      },
      {
        "category": "GOBIERNOS_OFICIALES",
        "matched_text": "asamblea nacional",
        "position": [
          591,
          608
        ],
        "start": 591,
        "end": 608
      },
      {
        "category": "GRUPOS_ESPECIFICOS",
        "matched_text": "extrema derecha",
        "position": [
          2041,
          2056
        ],
        "start": 2041,
        "end": 2056
      },
      {
        "category": "PAISES",
        "matched_text": "estados unidos",
        "position": [
          228,
          242
        ],
        "start": 228,
        "end": 242
      },
      {
        "category": "PAISES",
        "matched_text": "venezuela",
        "position": [
          22,
          31
        ],
        "start": 22,
        "end": 31
      },
      {
        "category": "ANTIIMPERIALISMO_SOBERANIA",
        "matched_text": "bloqueo",
        "position": [
          1903,
          1910
        ],
        "start": 1903,
        "end": 1910
      }
    ],
    "match_count": 10
  },
  "knowledge_graph": {
    "entidades": [
      {
        "nombre": "Delcy Rodríguez",
        "tipo": "Persona"
      },
      {
        "nombre": "Venezuela",
        "tipo": "Lugar"
      },
      {
        "nombre": "EE.UU.",
        "tipo": "Lugar"
      },
      {
        "nombre": "Nicolás Maduro",
        "tipo": "Persona"
      },
      {
        "nombre": "Asamblea Nacional",
        "tipo": "Organizacion"
      },
      {
        "nombre": "Maduro",
        "tipo": "Persona"
      },
      {
        "nombre": "Rodríguez",
        "tipo": "Persona"
      },
      {
        "nombre": "Chevron",
        "tipo": "Organizacion"
      },
      {
        "nombre": "la Machado",
        "tipo": "Persona"
      },
      {
        "nombre": "Trump",
        "tipo": "Persona"
      },
      {
        "nombre": "Estados Unidos",
        "tipo": "Lugar"
      },
      {
        "nombre": "China",
        "tipo": "Lugar"
      },
      {
        "nombre": "Donald Trump",
        "tipo": "Persona"
      },
      {
        "nombre": "Gobierno",
        "tipo": "Lugar"
      },
      {
        "nombre": "María Elvira Salazar",
        "tipo": "Persona"
      }
    ],
    "relaciones": [
      {
        "sujeto": "Venezuela",
        "relacion": "ASEGURAR",
        "objeto": "Estados Unidos"
      },
      {
        "sujeto": "Venezuela",
        "relacion": "ASEGURAR",
        "objeto": "EE.UU."
      },
      {
        "sujeto": "Delcy Rodríguez",
        "relacion": "ASEGURAR",
        "objeto": "Estados Unidos"
      },
      {
        "sujeto": "Delcy Rodríguez",
        "relacion": "ASEGURAR",
        "objeto": "EE.UU."
      },
      {
        "sujeto": "Venezuela",
        "relacion": "MANTENER_INDICAR",
        "objeto": "Asamblea Nacional"
      },
      {
        "sujeto": "Venezuela",
        "relacion": "MANTENER_INDICAR",
        "objeto": "Nicolás Maduro"
      },
      {
        "sujeto": "Rodríguez",
        "relacion": "RESALTAR",
        "objeto": "Estados Unidos"
      },
      {
        "sujeto": "Rodríguez",
        "relacion": "RESALTAR",
        "objeto": "Donald Trump"
      },
      {
        "sujeto": "Rodríguez",
        "relacion": "RESALTAR",
        "objeto": "China"
      },
      {
        "sujeto": "Estados Unidos",
        "relacion": "IMPONER_RESALTAR",
        "objeto": "China"
      },
      {
        "sujeto": "Donald Trump",
        "relacion": "IMPONER_RESALTAR",
        "objeto": "China"
      },
      {
        "sujeto": "Estados Unidos",
        "relacion": "MENCIONAR",
        "objeto": "Trump"
      },
      {
        "sujeto": "Rodríguez",
        "relacion": "SE_ALAR",
        "objeto": "Maduro"
      },
      {
        "sujeto": "Rodríguez",
        "relacion": "SE_ALAR",
        "objeto": "EE.UU."
      },
      {
        "sujeto": "Rodríguez",
        "relacion": "SE_ALAR",
        "objeto": "Venezuela"
      },
      {
        "sujeto": "Maduro",
        "relacion": "RECHAZAR_SE_ALAR",
        "objeto": "EE.UU."
      },
      {
        "sujeto": "Maduro",
        "relacion": "RECHAZAR_SE_ALAR",
        "objeto": "Venezuela"
      },
      {
        "sujeto": "EE.UU.",
        "relacion": "RECHAZAR_SE_ALAR",
        "objeto": "Venezuela"
      },
      {
        "sujeto": "Estados Unidos",
        "relacion": "EJERCER_ABORDAR_DECIR",
        "objeto": "Venezuela"
      },
      {
        "sujeto": "Chevron",
        "relacion": "MENCIONAR",
        "objeto": "María Elvira Salazar"
      },
      {
        "sujeto": "la Machado",
        "relacion": "PEDIR_HACER_GRITAR",
        "objeto": "Venezuela"
      },
      {
        "sujeto": "la Machado",
        "relacion": "PEDIR_HACER_GRITAR",
        "objeto": "Chevron"
      },
      {
        "sujeto": "Venezuela",
        "relacion": "PEDIR_HACER_GRITAR",
        "objeto": "Chevron"
      },
      {
        "sujeto": "la Machado",
        "relacion": "PEDIR_HABER_GRITAR",
        "objeto": "Chevron"
      },
      {
        "sujeto": "la Machado",
        "relacion": "PEDIR_HABER_GRITAR",
        "objeto": "Venezuela"
      },
      {
        "sujeto": "Chevron",
        "relacion": "QUITAR_L_HABER_GRITAR",
        "objeto": "Venezuela"
      },
      {
        "sujeto": "Chevron",
        "relacion": "DECIR_HABER_GRITAR",
        "objeto": "Venezuela"
      }
    ]
  },
  "sentiment": {
    "compound": 0.4588,
    "pos": 0.024,
    "neu": 0.962,
    "neg": 0.014,
    "label": "positive"
  },
  "_file_path": "Data/Data_articles/Data_articles2/article_875.json",
  "vector": [
    0.0,
    0.0,
    0.0,
    0.0,
    0.0,
    0.0,
    0.0,
    0.0,
    0.0,
    0.0,
    0.0,
    0.0,
    0.0,
    0.0,
    0.0,
    0.0,
    0.0,
    0.0,
    0.0,
    0.0,
    0.0,
    0.0,
    0.0,
    0.0,
    0.0,
    0.0,
    0.0,
    0.0,
    0.0,
    0.0,
    0.0,
    0.0,
    0.0,
    0.0,
    0.0,
    0.0,
    0.0,
    0.0,
    0.0,
    0.0,
    0.0,
    0.0,
    0.0,
    0.0,
    0.0,
    0.0,
    0.0,
    0.0,
    0.0,
    0.0,
    0.0,
    0.0,
    0.0,
    0.0,
    0.0,
    0.0,
    0.06922344177335753,
    0.0,
    0.0,
    0.0,
    0.07359034085501066,
    0.0,
    0.0,
    0.0,
    0.0,
    0.0,
    0.0,
    0.0,
    0.0,
    0.0,
    0.0,
    0.0,
    0.0,
    0.0,
    0.0,
    0.0,
    0.0,
    0.0,
    0.0,
    0.0,
    0.0,
    0.0,
    0.0,
    0.0,
    0.0,
    0.0,
    0.0,
    0.0,
    0.0,
    0.0,
    0.0,
    0.0,
    0.0,
    0.0,
    0.0,
    0.0,
    0.0,
    0.0,
    0.0,
    0.0,
    0.0,
    0.0,
    0.0,
    0.0,
    0.0,
    0.0,
    0.05099089202952585,
    0.06345475731996116,
    0.0,
    0.0,
    0.0,
    0.0,
    0.0,
    0.0,
    0.0,
    0.0,
    0.03668281891059493,
    0.0,
    0.0,
    0.0,
    0.0,
    0.0,
    0.0,
    0.0,
    0.0,
    0.07201292364071,
    0.0,
    0.0,
    0.0,
    0.0,
    0.0,
    0.0,
    0.0,
    0.0,
    0.0,
    0.0,
    0.0,
    0.0,
    0.0,
    0.0,
    0.0,
    0.0,
    0.0,
    0.0,
    0.0,
    0.0,
    0.0,
    0.0,
    0.0,
    0.0,
    0.0,
    0.0,
    0.0,
    0.0,
    0.0,
    0.0,
    0.0,
    0.0,
    0.0,
    0.0,
    0.0,
    0.0,
    0.0,
    0.0,
    0.0,
    0.0,
    0.0,
    0.0,
    0.0,
    0.0,
    0.0,
    0.0,
    0.0,
    0.0,
    0.0,
    0.0,
    0.0,
    0.0,
    0.0,
    0.0,
    0.0,
    0.0,
    0.0,
    0.0,
    0.0,
    0.0,
    0.0,
    0.0,
    0.0,
    0.0,
    0.0,
    0.0,
    0.1181819020588875,
    0.0,
    0.0,
    0.0,
    0.0,
    0.0,
    0.0,
    0.0,
    0.0,
    0.0,
    0.0,
    0.0,
    0.0,
    0.05498687544433699,
    0.06236625296169625,
    0.0,
    0.0,
    0.043304249271403465,
    0.0,
    0.0,
    0.0,
    0.0,
    0.0,
    0.0,
    0.0,
    0.0,
    0.0,
    0.0,
    0.0,
    0.0,
    0.0,
    0.0,
    0.0,
    0.0,
    0.0,
    0.0,
    0.0,
    0.0,
    0.0,
    0.0,
    0.0,
    0.0,
    0.0,
    0.0,
    0.0,
    0.0,
    0.0,
    0.0,
    0.0,
    0.0,
    0.0,
    0.0,
    0.0,
    0.0,
    0.0,
    0.0,
    0.0,
    0.0,
    0.0,
    0.0,
    0.0,
    0.0,
    0.0,
    0.0,
    0.0,
    0.0,
    0.0,
    0.0,
    0.0,
    0.0,
    0.0,
    0.0,
    0.0,
    0.0,
    0.0,
    0.0,
    0.0,
    0.0,
    0.0,
    0.0,
    0.0,
    0.0,
    0.0,
    0.0,
    0.0,
    0.0,
    0.0,
    0.0,
    0.0,
    0.0,
    0.0,
    0.0,
    0.0,
    0.0,
    0.0,
    0.0,
    0.05940080322818772,
    0.0,
    0.0,
    0.0,
    0.0,
    0.0,
    0.0,
    0.0,
    0.0,
    0.0,
    0.0,
    0.0,
    0.0,
    0.0,
    0.0,
    0.0,
    0.0,
    0.0,
    0.0,
    0.0,
    0.0,
    0.0,
    0.0,
    0.0,
    0.0,
    0.0,
    0.0,
    0.0,
    0.0,
    0.0,
    0.0,
    0.06074140750591491,
    0.0,
    0.0,
    0.0,
    0.0,
    0.0,
    0.0,
    0.0,
    0.0,
    0.0,
    0.0,
    0.0,
    0.0,
    0.0,
    0.0,
    0.0,
    0.0,
    0.0,
    0.0,
    0.0,
    0.0,
    0.0,
    0.0,
    0.0,
    0.0,
    0.0,
    0.0,
    0.0,
    0.0,
    0.0,
    0.0,
    0.0,
    0.0,
    0.0,
    0.0,
    0.0,
    0.0,
    0.0,
    0.0,
    0.0,
    0.0,
    0.0,
    0.0,
    0.0,
    0.0,
    0.0,
    0.0,
    0.0,
    0.0,
    0.0,
    0.0,
    0.0,
    0.0,
    0.0,
    0.0,
    0.0,
    0.0,
    0.051920321278162075,
    0.0,
    0.0,
    0.0,
    0.046477971349407614,
    0.0,
    0.0,
    0.0,
    0.0,
    0.0,
    0.0,
    0.0,
    0.0,
    0.0,
    0.0,
    0.0,
    0.0,
    0.0,
    0.0,
    0.0,
    0.0,
    0.0,
    0.0,
    0.0,
    0.061641311290856496,
    0.0,
    0.0,
    0.0,
    0.0,
    0.0,
    0.0,
    0.0,
    0.0,
    0.0,
    0.0,
    0.0,
    0.0,
    0.0,
    0.0,
    0.0,
    0.06154400753951562,
    0.0,
    0.0,
    0.0,
    0.0,
    0.0,
    0.0,
    0.0,
    0.0,
    0.0,
    0.0,
    0.0,
    0.0,
    0.0,
    0.0,
    0.0,
    0.0,
    0.0,
    0.0,
    0.0,
    0.0,
    0.0,
    0.0,
    0.0,
    0.0,
    0.0,
    0.0,
    0.0,
    0.0,
    0.03179299579744733,
    0.050217978137211614,
    0.0,
    0.0,
    0.0,
    0.0,
    0.0,
    0.0,
    0.0,
    0.0,
    0.0,
    0.0,
    0.0,
    0.0,
    0.0,
    0.0,
    0.0,
    0.0,
    0.0,
    0.0,
    0.0,
    0.0,
    0.0,
    0.0,
    0.0,
    0.0,
    0.0,
    0.06378884611556558,
    0.0,
    0.0,
    0.0,
    0.0,
    0.0,
    0.0,
    0.0,
    0.0,
    0.0,
    0.0,
    0.0,
    0.0,
    0.0,
    0.0,
    0.0,
    0.0,
    0.0,
    0.0,
    0.05842400220602388,
    0.0,
    0.06381624666562694,
    0.0,
    0.04287093980309395,
    0.0,
    0.0,
    0.0,
    0.0,
    0.0,
    0.0,
    0.0,
    0.0,
    0.0,
    0.0,
    0.0,
    0.0,
    0.0,
    0.0,
    0.0,
    0.0,
    0.0,
    0.0,
    0.0,
    0.0,
    0.0,
    0.0,
    0.06526679143292496,
    0.0,
    0.0,
    0.0,
    0.0,
    0.0,
    0.0,
    0.0,
    0.0,
    0.0,
    0.0,
    0.0,
    0.0,
    0.0,
    0.0,
    0.0,
    0.0,
    0.0,
    0.0,
    0.0,
    0.0,
    0.0,
    0.0,
    0.0,
    0.0,
    0.0,
    0.0,
    0.0,
    0.0,
    0.0,
    0.0,
    0.0,
    0.0,
    0.0,
    0.0,
    0.0,
    0.0,
    0.0,
    0.0,
    0.0,
    0.057730919707261553,
    0.0,
    0.0,
    0.0,
    0.0,
    0.0,
    0.0,
    0.0,
    0.0,
    0.0,
    0.0,
    0.0,
    0.0,
    0.0,
    0.0,
    0.0,
    0.0,
    0.0,
    0.0,
    0.0,
    0.0,
    0.0,
    0.0,
    0.0,
    0.0,
    0.0,
    0.0,
    0.0,
    0.0,
    0.0,
    0.0,
    0.0,
    0.0,
    0.0,
    0.0,
    0.0,
    0.0,
    0.0,
    0.0,
    0.0,
    0.0,
    0.0,
    0.0,
    0.0,
    0.0,
    0.0,
    0.0,
    0.0,
    0.0,
    0.0,
    0.0,
    0.0,
    0.0,
    0.0,
    0.0,
    0.0,
    0.06094972553345231,
    0.0,
    0.0,
    0.0,
    0.0,
    0.049701856294367665,
    0.0,
    0.07484148288731865,
    0.0,
    0.0,
    0.0,
    0.0,
    0.0,
    0.0,
    0.0,
    0.0,
    0.0,
    0.0,
    0.0,
    0.0,
    0.0,
    0.0,
    0.0,
    0.0,
    0.0,
    0.0,
    0.0,
    0.02310588502415637,
    0.0,
    0.0,
    0.020737795880082045,
    0.0,
    0.0,
    0.0,
    0.0,
    0.0,
    0.0,
    0.0,
    0.0,
    0.0,
    0.0,
    0.0,
    0.0,
    0.0,
    0.0,
    0.0,
    0.0,
    0.0,
    0.0,
    0.0,
    0.0,
    0.0,
    0.0,
    0.06914283366013035,
    0.0,
    0.07664908573751272,
    0.0,
    0.0,
    0.0,
    0.0,
    0.0,
    0.0,
    0.0,
    0.0,
    0.0,
    0.0,
    0.0,
    0.0,
    0.0,
    0.0,
    0.0,
    0.0,
    0.07048749498203247,
    0.0,
    0.0,
    0.0,
    0.0,
    0.06656357571723119,
    0.06520479803745086,
    0.0,
    0.031487806434639345,
    0.05949445586698029,
    0.07545769883947766,
    0.0,
    0.0,
    0.0,
    0.0,
    0.0,
    0.0,
    0.050930926345315056,
    0.0,
    0.0,
    0.0,
    0.0,
    0.0,
    0.0,
    0.0,
    0.0,
    0.0,
    0.0,
    0.0,
    0.0,
    0.0,
    0.0,
    0.0,
    0.0,
    0.0,
    0.0,
    0.07044360187902964,
    0.0,
    0.0,
    0.0,
    0.0,
    0.06378884611556558,
    0.0,
    0.0,
    0.0,
    0.0,
    0.0,
    0.0,
    0.0,
    0.0,
    0.0,
    0.0,
    0.0,
    0.0,
    0.0,
    0.0,
    0.0,
    0.0,
    0.0,
    0.0,
    0.0,
    0.0,
    0.0,
    0.09369159778332743,
    0.0,
    0.0,
    0.0,
    0.0,
    0.0,
    0.0,
    0.0,
    0.0,
    0.0,
    0.0,
    0.0,
    0.0,
    0.0,
    0.0,
    0.0,
    0.0,
    0.0,
    0.0,
    0.0,
    0.0,
    0.0,
    0.0,
    0.0,
    0.0,
    0.0,
    0.0,
    0.0,
    0.0,
    0.0,
    0.0,
    0.0,
    0.0,
    0.0,
    0.0,
    0.0,
    0.05771211623126556,
    0.044787615553338614,
    0.060221795040664876,
    0.0,
    0.0,
    0.0,
    0.0,
    0.0,
    0.0,
    0.0,
    0.0,
    0.026783592687104802,
    0.0,
    0.0,
    0.0,
    0.0,
    0.0,
    0.0,
    0.0,
    0.0,
    0.04294112376389507,
    0.0,
    0.0,
    0.0,
    0.0,
    0.0,
    0.0,
    0.0,
    0.0,
    0.0,
    0.0,
    0.0,
    0.0,
    0.0,
    0.0,
    0.0,
    0.0,
    0.0,
    0.0,
    0.0,
    0.0,
    0.0,
    0.0,
    0.0,
    0.0,
    0.0,
    0.0,
    0.0438696736876927,
    0.0,
    0.06046806584660526,
    0.0,
    0.0,
    0.0,
    0.0,
    0.0,
    0.0,
    0.0,
    0.0,
    0.0,
    0.0,
    0.06318191177077774,
    0.0,
    0.0,
    0.0,
    0.0,
    0.0,
    0.06069550402872666,
    0.0,
    0.0,
    0.0,
    0.0,
    0.0,
    0.0,
    0.0,
    0.0,
    0.0,
    0.0,
    0.050013902011097726,
    0.050172387876043154,
    0.05804113680655354,
    0.0,
    0.0,
    0.0,
    0.0,
    0.0,
    0.0,
    0.0,
    0.0,
    0.0,
    0.0,
    0.0,
    0.0,
    0.0,
    0.0,
    0.0,
    0.0,
    0.0,
    0.0,
    0.0,
    0.0,
    0.0,
    0.0,
    0.0527210657592601,
    0.0,
    0.0,
    0.0,
    0.0,
    0.0,
    0.0,
    0.0,
    0.0,
    0.07543117072863531,
    0.07545769883947766,
    0.0,
    0.0,
    0.0,
    0.0,
    0.0,
    0.0,
    0.0,
    0.0,
    0.0,
    0.0,
    0.0,
    0.0,
    0.0,
    0.0,
    0.0,
    0.0,
    0.0,
    0.0,
    0.0,
    0.0,
    0.0,
    0.06910269110730964,
    0.07009699569960556,
    0.0,
    0.0,
    0.0,
    0.0,
    0.0,
    0.0,
    0.0,
    0.0,
    0.0,
    0.0,
    0.0,
    0.0,
    0.0,
    0.0,
    0.0,
    0.0,
    0.0,
    0.056555131877944156,
    0.0,
    0.0,
    0.0,
    0.0,
    0.0,
    0.0,
    0.0,
    0.0,
    0.0,
    0.0,
    0.0,
    0.0,
    0.0,
    0.0,
    0.0,
    0.0,
    0.0,
    0.0,
    0.0,
    0.0,
    0.0,
    0.0,
    0.0,
    0.0,
    0.0,
    0.09826182814035372,
    0.0,
    0.0,
    0.0,
    0.0,
    0.0,
    0.0,
    0.0,
    0.0,
    0.0,
    0.0,
    0.0,
    0.0,
    0.0,
    0.06690603647346648,
    0.0,
    0.0,
    0.0,
    0.11376142384656025,
    0.0,
    0.0,
    0.0,
    0.0,
    0.0,
    0.0,
    0.0,
    0.0,
    0.0,
    0.0,
    0.09601918966724056,
    0.0,
    0.0,
    0.0,
    0.06762722652600575,
    0.0,
    0.0,
    0.0,
    0.0,
    0.0,
    0.0,
    0.05476899660026076,
    0.0,
    0.0,
    0.0,
    0.0,
    0.0,
    0.0,
    0.0,
    0.0,
    0.0,
    0.0,
    0.0,
    0.0,
    0.0,
    0.0,
    0.0,
    0.0,
    0.0,
    0.0,
    0.0,
    0.0,
    0.0,
    0.0,
    0.0,
    0.0,
    0.0,
    0.0,
    0.0,
    0.0,
    0.0,
    0.0,
    0.0693859663519365,
    0.0,
    0.0,
    0.0,
    0.0,
    0.0,
    0.0,
    0.0,
    0.0,
    0.05669497825475851,
    0.06922344177335753,
    0.0,
    0.0,
    0.0,
    0.06270293180858896,
    0.10115036602192658,
    0.0,
    0.0,
    0.0,
    0.0,
    0.0,
    0.0,
    0.0,
    0.0,
    0.0,
    0.03232745487929097,
    0.0,
    0.0,
    0.05423772657805312,
    0.0,
    0.0,
    0.0,
    0.0,
    0.0,
    0.01906722080088727,
    0.0,
    0.0,
    0.0,
    0.0,
    0.0,
    0.0,
    0.0,
    0.0,
    0.0,
    0.0,
    0.0,
    0.0,
    0.0,
    0.0,
    0.0,
    0.031752835371696715,
    0.0,
    0.0,
    0.05809272838601029,
    0.0,
    0.0,
    0.0,
    0.0,
    0.0,
    0.0,
    0.0,
    0.0,
    0.0,
    0.0,
    0.0,
    0.0,
    0.0,
    0.0,
    0.0,
    0.0,
    0.0,
    0.0,
    0.0,
    0.0,
    0.0,
    0.0,
    0.0,
    0.0,
    0.0,
    0.0,
    0.0,
    0.0,
    0.0,
    0.0,
    0.0,
    0.0,
    0.0,
    0.0,
    0.0,
    0.0,
    0.0,
    0.0,
    0.0,
    0.0,
    0.0,
    0.0,
    0.0,
    0.07243645300325677,
    0.1391578458788718,
    0.05049446183078822,
    0.0,
    0.0,
    0.0,
    0.0,
    0.0,
    0.0,
    0.12523815680610578,
    0.0,
    0.0,
    0.0,
    0.0,
    0.0,
    0.0,
    0.0,
    0.0,
    0.0,
    0.11542199514383636,
    0.0,
    0.0,
    0.0,
    0.0,
    0.0,
    0.0,
    0.0,
    0.0,
    0.0,
    0.0,
    0.0,
    0.0,
    0.0,
    0.05856736775711007,
    0.0,
    0.0,
    0.0,
    0.0,
    0.0,
    0.0,
    0.0,
    0.0,
    0.0,
    0.0,
    0.0,
    0.07873823733071962,
    0.08627851751995017,
    0.04414150508956623,
    0.0,
    0.0,
    0.0,
    0.0,
    0.0,
    0.0,
    0.01858629276243762,
    0.0,
    0.0,
    0.0,
    0.0,
    0.050847374213063394,
    0.0,
    0.0,
    0.0,
    0.0,
    0.0,
    0.0,
    0.0,
    0.0,
    0.0,
    0.0,
    0.0,
    0.0,
    0.0,
    0.0,
    0.0,
    0.0,
    0.0,
    0.03500501247859912,
    0.0,
    0.0,
    0.0,
    0.0,
    0.0,
    0.0,
    0.0,
    0.0,
    0.0,
    0.0,
    0.0,
    0.0,
    0.0,
    0.0,
    0.0,
    0.0,
    0.0,
    0.0,
    0.0,
    0.0,
    0.0,
    0.0,
    0.0,
    0.0,
    0.0,
    0.0,
    0.0,
    0.0,
    0.0,
    0.0,
    0.0,
    0.0629405142666809,
    0.06729197866801137,
    0.0,
    0.0,
    0.0,
    0.0,
    0.0,
    0.0,
    0.0,
    0.0,
    0.0,
    0.0,
    0.0,
    0.0,
    0.0,
    0.0,
    0.0,
    0.0,
    0.0,
    0.0,
    0.0,
    0.0,
    0.0,
    0.0,
    0.0,
    0.0,
    0.0,
    0.0,
    0.0,
    0.0,
    0.0,
    0.06583654548955829,
    0.0,
    0.0,
    0.0,
    0.0,
    0.0,
    0.0,
    0.0,
    0.0,
    0.0,
    0.0,
    0.0,
    0.0,
    0.0,
    0.0,
    0.0,
    0.0,
    0.0,
    0.0,
    0.0,
    0.0,
    0.0,
    0.0,
    0.0,
    0.0,
    0.0,
    0.0,
    0.0,
    0.0,
    0.0,
    0.0,
    0.0,
    0.0,
    0.0,
    0.0,
    0.0,
    0.0,
    0.0,
    0.0,
    0.0,
    0.0,
    0.0,
    0.0,
    0.0,
    0.0,
    0.0,
    0.0,
    0.0,
    0.11972058086250362,
    0.0,
    0.0,
    0.0,
    0.0,
    0.0,
    0.0,
    0.0,
    0.0,
    0.0,
    0.0,
    0.0,
    0.0,
    0.0,
    0.0,
    0.0,
    0.0,
    0.0,
    0.0,
    0.028894295732973124,
    0.0,
    0.0,
    0.0,
    0.0,
    0.0,
    0.0,
    0.0,
    0.0,
    0.0,
    0.0,
    0.0,
    0.0,
    0.0,
    0.0,
    0.0,
    0.0,
    0.0,
    0.0,
    0.07172428543577967,
    0.0,
    0.0,
    0.0,
    0.061066773569936166,
    0.0,
    0.0,
    0.0,
    0.0,
    0.0,
    0.04743337599593487,
    0.0,
    0.0,
    0.0,
    0.0,
    0.0,
    0.0,
    0.0,
    0.0,
    0.0,
    0.0,
    0.0,
    0.0,
    0.0,
    0.0,
    0.0,
    0.0,
    0.0,
    0.0,
    0.0,
    0.0,
    0.0,
    0.0,
    0.0,
    0.0,
    0.0,
    0.0,
    0.0,
    0.0,
    0.0,
    0.0,
    0.0,
    0.0,
    0.0,
    0.0,
    0.0,
    0.0,
    0.0,
    0.0,
    0.0,
    0.0,
    0.0,
    0.0,
    0.0,
    0.0,
    0.0,
    0.0,
    0.0,
    0.0,
    0.0,
    0.0,
    0.0,
    0.0,
    0.0,
    0.0,
    0.06334502415319636,
    0.0,
    0.0,
    0.0,
    0.0,
    0.0,
    0.0,
    0.0,
    0.0,
    0.0,
    0.0,
    0.0,
    0.0,
    0.0,
    0.0,
    0.0,
    0.0,
    0.0,
    0.0,
    0.0,
    0.07139339413179882,
    0.0,
    0.0,
    0.0,
    0.0,
    0.0,
    0.06817008968214142,
    0.0,
    0.0,
    0.0,
    0.0,
    0.0,
    0.0,
    0.0,
    0.0,
    0.0,
    0.0,
    0.047404948548890824,
    0.0,
    0.0,
    0.0,
    0.0,
    0.0,
    0.0,
    0.0,
    0.0,
    0.0,
    0.0,
    0.0,
    0.0,
    0.0,
    0.0,
    0.0,
    0.0,
    0.0,
    0.0,
    0.0,
    0.0,
    0.0,
    0.08947081356666647,
    0.09980291862675325,
    0.0,
    0.0,
    0.0,
    0.0,
    0.0,
    0.0,
    0.0,
    0.0,
    0.0,
    0.0,
    0.0,
    0.0,
    0.0,
    0.0,
    0.0,
    0.0,
    0.0,
    0.0,
    0.0,
    0.0,
    0.0,
    0.0,
    0.0,
    0.0,
    0.057730919707261553,
    0.0,
    0.03581482889429882,
    0.0,
    0.0,
    0.0,
    0.0,
    0.0,
    0.0,
    0.0,
    0.0,
    0.0,
    0.0,
    0.0,
    0.0,
    0.0,
    0.0,
    0.0,
    0.0,
    0.0,
    0.0,
    0.0,
    0.0,
    0.0,
    0.0,
    0.0,
    0.0,
    0.0,
    0.0,
    0.0,
    0.0,
    0.0,
    0.0,
    0.0,
    0.0,
    0.0,
    0.0,
    0.0,
    0.0,
    0.0,
    0.0,
    0.0,
    0.0,
    0.0,
    0.0,
    0.0,
    0.0,
    0.044668774008773886,
    0.0,
    0.0,
    0.0,
    0.0,
    0.0,
    0.0,
    0.0,
    0.0,
    0.0,
    0.0,
    0.0,
    0.0,
    0.0,
    0.0,
    0.0,
    0.0,
    0.0,
    0.0,
    0.0,
    0.0,
    0.0,
    0.0,
    0.05641657442616156,
    0.0,
    0.0,
    0.0,
    0.0,
    0.0,
    0.0,
    0.0,
    0.0,
    0.0,
    0.0,
    0.0,
    0.0,
    0.0,
    0.0,
    0.0,
    0.0,
    0.0,
    0.0,
    0.0,
    0.0,
    0.0,
    0.0,
    0.0,
    0.0,
    0.0,
    0.0,
    0.0,
    0.0,
    0.0,
    0.0,
    0.0,
    0.0,
    0.0,
    0.0,
    0.0,
    0.0,
    0.0,
    0.0,
    0.0,
    0.0,
    0.0,
    0.06636178239077226,
    0.0,
    0.0,
    0.07035619827760128,
    0.0,
    0.0,
    0.0706643602820069,
    0.0,
    0.0,
    0.0,
    0.0,
    0.0,
    0.0,
    0.0,
    0.0,
    0.0,
    0.0,
    0.0,
    0.0,
    0.0,
    0.0,
    0.0,
    0.06839787248074475,
    0.0,
    0.0,
    0.0,
    0.0,
    0.0,
    0.0,
    0.0,
    0.0,
    0.0,
    0.0,
    0.0,
    0.0,
    0.0,
    0.0,
    0.0,
    0.0,
    0.0,
    0.0,
    0.0,
    0.0,
    0.0,
    0.0,
    0.0,
    0.0,
    0.0,
    0.0,
    0.0,
    0.0,
    0.0,
    0.0,
    0.0,
    0.0,
    0.0,
    0.0,
    0.0,
    0.0,
    0.0,
    0.0,
    0.0,
    0.0,
    0.0,
    0.0,
    0.0,
    0.0,
    0.0,
    0.0,
    0.0,
    0.0,
    0.0,
    0.0,
    0.0,
    0.0,
    0.05748829010516799,
    0.0,
    0.0,
    0.0,
    0.0,
    0.0,
    0.0,
    0.11230376368527423,
    0.0,
    0.0,
    0.0,
    0.0,
    0.0,
    0.0,
    0.0,
    0.0,
    0.0,
    0.0,
    0.0,
    0.0,
    0.0,
    0.0,
    0.0,
    0.0,
    0.0,
    0.0,
    0.0,
    0.0,
    0.0,
    0.0,
    0.0,
    0.0,
    0.0,
    0.0,
    0.0,
    0.0,
    0.0,
    0.0,
    0.1409968096778774,
    0.0,
    0.0,
    0.0,
    0.0,
    0.0,
    0.0,
    0.0,
    0.0,
    0.0,
    0.0,
    0.0,
    0.0,
    0.0,
    0.0,
    0.0,
    0.0,
    0.0571224964603455,
    0.0,
    0.0,
    0.0,
    0.0,
    0.0,
    0.0,
    0.0,
    0.0,
    0.0,
    0.0,
    0.12536267717319363,
    0.0,
    0.0,
    0.0,
    0.0,
    0.06033323644867907,
    0.0,
    0.0,
    0.0,
    0.06715048701555608,
    0.0,
    0.0,
    0.0,
    0.0,
    0.0,
    0.0,
    0.0,
    0.0,
    0.0,
    0.0,
    0.0,
    0.0,
    0.0,
    0.0,
    0.0,
    0.0,
    0.0,
    0.0,
    0.0,
    0.0,
    0.0,
    0.0,
    0.11465132271280876,
    0.0,
    0.0,
    0.0,
    0.0,
    0.0,
    0.0,
    0.0,
    0.06776124582501739,
    0.0,
    0.0,
    0.0,
    0.0,
    0.0,
    0.0,
    0.0,
    0.0,
    0.0,
    0.0,
    0.0,
    0.0,
    0.0,
    0.0,
    0.0,
    0.0,
    0.0,
    0.0,
    0.0,
    0.0,
    0.0,
    0.0249267096110198,
    0.0,
    0.0,
    0.03205668670763016,
    0.0,
    0.0,
    0.0,
    0.0,
    0.0,
    0.06930448443376858,
    0.0,
    0.0,
    0.0,
    0.0,
    0.0,
    0.0,
    0.0,
    0.0,
    0.0,
    0.0,
    0.0,
    0.0,
    0.0,
    0.0,
    0.0,
    0.0,
    0.0,
    0.0,
    0.0,
    0.0,
    0.0,
    0.0,
    0.0,
    0.0,
    0.0,
    0.06768809056095668,
    0.0,
    0.0,
    0.0,
    0.0,
    0.0,
    0.0,
    0.0,
    0.0,
    0.0,
    0.0,
    0.0,
    0.0,
    0.0,
    0.0,
    0.0,
    0.0,
    0.0,
    0.0,
    0.0,
    0.0,
    0.0,
    0.0,
    0.0,
    0.0,
    0.0,
    0.0,
    0.0,
    0.0,
    0.0,
    0.0,
    0.0,
    0.0,
    0.0,
    0.0,
    0.0,
    0.0,
    0.0,
    0.0,
    0.0,
    0.0,
    0.0,
    0.0,
    0.0,
    0.0,
    0.0,
    0.0,
    0.0,
    0.13188106197608132,
    0.0,
    0.0,
    0.08107788290860976,
    0.0,
    0.0,
    0.0,
    0.0,
    0.0,
    0.0,
    0.0,
    0.0,
    0.0,
    0.0,
    0.0,
    0.0,
    0.07048749498203247,
    0.0,
    0.0,
    0.0,
    0.0,
    0.0,
    0.0,
    0.0,
    0.0,
    0.062264158327553186,
    0.0,
    0.0,
    0.0,
    0.0,
    0.0,
    0.0,
    0.0,
    0.0,
    0.0,
    0.0,
    0.0,
    0.0,
    0.0,
    0.0,
    0.0,
    0.0,
    0.04605669328649176,
    0.0,
    0.0,
    0.0,
    0.0,
    0.0,
    0.0,
    0.0,
    0.0,
    0.0,
    0.11082379803742415,
    0.0,
    0.0,
    0.0,
    0.0,
    0.0,
    0.06619566603649854,
    0.0,
    0.0,
    0.0,
    0.0,
    0.05089506141276059,
    0.0,
    0.0,
    0.0,
    0.0,
    0.0,
    0.0,
    0.0,
    0.0,
    0.0,
    0.0,
    0.0,
    0.0,
    0.0,
    0.0,
    0.0,
    0.0,
    0.0,
    0.0,
    0.0,
    0.0,
    0.0,
    0.0,
    0.0,
    0.0,
    0.0,
    0.0,
    0.0,
    0.0,
    0.0,
    0.0,
    0.0,
    0.0,
    0.0,
    0.0,
    0.0,
    0.0,
    0.0,
    0.0509548839234513,
    0.0,
    0.0,
    0.0,
    0.0,
    0.0,
    0.0,
    0.0,
    0.0,
    0.0,
    0.0,
    0.0,
    0.0,
    0.0,
    0.0,
    0.0,
    0.0,
    0.0,
    0.0,
    0.0,
    0.0,
    0.0,
    0.0,
    0.0,
    0.0,
    0.0,
    0.0,
    0.0,
    0.0,
    0.11358710133089697,
    0.0,
    0.0,
    0.0,
    0.0,
    0.0,
    0.0,
    0.0,
    0.02293388082306936,
    0.0,
    0.033501803311000715,
    0.0,
    0.0,
    0.0,
    0.0,
    0.0,
    0.0,
    0.0,
    0.0,
    0.0,
    0.0,
    0.030613934721679153,
    0.0,
    0.0,
    0.0,
    0.05858245824059103,
    0.0,
    0.0,
    0.04240897441684883,
    0.0,
    0.0,
    0.0,
    0.0,
    0.0,
    0.0,
    0.0,
    0.0,
    0.0,
    0.0,
    0.0,
    0.0,
    0.048013513977137344,
    0.04853507102660972,
    0.0,
    0.0,
    0.0,
    0.0,
    0.0,
    0.0,
    0.0,
    0.022156821903348972,
    0.0,
    0.0,
    0.0,
    0.0,
    0.06367665621355832,
    0.0,
    0.0,
    0.0,
    0.0,
    0.0,
    0.0,
    0.0,
    0.0,
    0.0,
    0.0,
    0.0,
    0.049234909970181616,
    0.0,
    0.0,
    0.0,
    0.0,
    0.0,
    0.0,
    0.0,
    0.06348231622245229,
    0.0,
    0.0,
    0.0,
    0.0,
    0.0,
    0.0,
    0.0,
    0.0,
    0.0,
    0.0,
    0.0,
    0.0,
    0.0,
    0.0,
    0.0,
    0.0,
    0.0,
    0.06364873907071882,
    0.0,
    0.0,
    0.0,
    0.0,
    0.0,
    0.0,
    0.0,
    0.0,
    0.0,
    0.0,
    0.0,
    0.0,
    0.0,
    0.0,
    0.0,
    0.0,
    0.0,
    0.0,
    0.0,
    0.0,
    0.0,
    0.0,
    0.0,
    0.0,
    0.05314495440511116,
    0.06996905129245638,
    0.0,
    0.0,
    0.0,
    0.0,
    0.0,
    0.0,
    0.0,
    0.0,
    0.0,
    0.0,
    0.0,
    0.0,
    0.0,
    0.0,
    0.0,
    0.0,
    0.0,
    0.0,
    0.0,
    0.0,
    0.0,
    0.0,
    0.0,
    0.0,
    0.0,
    0.0,
    0.0,
    0.0,
    0.0,
    0.0,
    0.0,
    0.0,
    0.0,
    0.0,
    0.0,
    0.0,
    0.0,
    0.0,
    0.0,
    0.0,
    0.0,
    0.0,
    0.0,
    0.0,
    0.0,
    0.0,
    0.0,
    0.0,
    0.0,
    0.0,
    0.0,
    0.0,
    0.0,
    0.0,
    0.0,
    0.0,
    0.0,
    0.0,
    0.0,
    0.0,
    0.0,
    0.0,
    0.0,
    0.0,
    0.0,
    0.0,
    0.0,
    0.0,
    0.0,
    0.0,
    0.0,
    0.0,
    0.0,
    0.0,
    0.0,
    0.0,
    0.0,
    0.0,
    0.0,
    0.06920678692857123,
    0.0,
    0.0,
    0.0,
    0.0,
    0.0,
    0.0,
    0.03722796981862058,
    0.0,
    0.07158131379243082,
    0.0,
    0.0,
    0.0,
    0.0,
    0.0,
    0.0,
    0.0,
    0.0,
    0.0,
    0.0,
    0.0,
    0.0,
    0.0,
    0.0,
    0.0,
    0.0,
    0.0,
    0.0,
    0.0,
    0.0,
    0.0,
    0.0,
    0.0,
    0.0,
    0.0,
    0.061616926245609056,
    0.0,
    0.11523132968266153,
    0.0,
    0.0,
    0.0,
    0.0,
    0.0,
    0.0,
    0.0,
    0.0,
    0.0,
    0.0,
    0.0,
    0.0,
    0.0,
    0.0,
    0.0,
    0.0,
    0.0,
    0.0,
    0.0,
    0.0,
    0.0,
    0.040284870609017205,
    0.0,
    0.0,
    0.0,
    0.0,
    0.0,
    0.0,
    0.0,
    0.0,
    0.0,
    0.0,
    0.046531470968499175,
    0.02878141754291087,
    0.0,
    0.0,
    0.0,
    0.029973990890005697,
    0.0,
    0.0,
    0.0,
    0.0,
    0.0,
    0.0,
    0.0379826326658177,
    0.0,
    0.0,
    0.0,
    0.0,
    0.0,
    0.0,
    0.0,
    0.0,
    0.0,
    0.05400097558906339,
    0.0,
    0.0,
    0.0,
    0.0,
    0.0,
    0.0,
    0.0,
    0.0,
    0.0,
    0.0,
    0.0,
    0.0,
    0.0,
    0.0,
    0.0,
    0.0,
    0.0,
    0.0,
    0.0,
    0.0,
    0.0,
    0.0,
    0.0,
    0.0,
    0.05741553564843877,
    0.03966127709008145,
    0.0,
    0.0,
    0.06035562420724525,
    0.0,
    0.0,
    0.07225817177290506,
    0.0,
    0.0,
    0.0,
    0.0,
    0.0,
    0.0,
    0.0,
    0.06583654548955829,
    0.0,
    0.055335766942802,
    0.0,
    0.0,
    0.0,
    0.0,
    0.0,
    0.0,
    0.0,
    0.0,
    0.0,
    0.044210237946856364,
    0.058035018614186445,
    0.0,
    0.0,
    0.10173976937672445,
    0.07409699916393761,
    0.0,
    0.0,
    0.0,
    0.0,
    0.0,
    0.0,
    0.0,
    0.0,
    0.0,
    0.0,
    0.1040393727637562,
    0.0,
    0.0,
    0.0,
    0.0,
    0.0,
    0.0,
    0.0,
    0.0,
    0.0,
    0.0,
    0.0,
    0.0,
    0.0,
    0.0,
    0.0,
    0.0,
    0.0,
    0.0,
    0.0,
    0.0,
    0.0,
    0.0,
    0.0,
    0.0,
    0.0,
    0.03662910158410593,
    0.0,
    0.0,
    0.0,
    0.0,
    0.0,
    0.0,
    0.0,
    0.04991289349829977,
    0.0,
    0.0,
    0.0,
    0.0,
    0.0,
    0.0,
    0.0,
    0.0,
    0.06835966819817911,
    0.0,
    0.0,
    0.0,
    0.0,
    0.0,
    0.0,
    0.0,
    0.0,
    0.0,
    0.0,
    0.0,
    0.0,
    0.0,
    0.061066773569936166,
    0.0,
    0.05221725465238425,
    0.0,
    0.0,
    0.0,
    0.0,
    0.0,
    0.0,
    0.0,
    0.0,
    0.0,
    0.0,
    0.0,
    0.0,
    0.05839404966329642,
    0.0,
    0.06348231622245229,
    0.0,
    0.0,
    0.0,
    0.0,
    0.06673383095821686,
    0.0,
    0.0,
    0.0,
    0.04628449885916086,
    0.0,
    0.06894318428363211,
    0.0,
    0.0,
    0.0,
    0.0,
    0.0,
    0.0,
    0.0,
    0.0,
    0.0,
    0.0,
    0.0,
    0.0,
    0.038628606635406015,
    0.0,
    0.0,
    0.0,
    0.07671545837114878,
    0.0,
    0.0,
    0.0,
    0.0,
    0.0,
    0.0,
    0.0,
    0.0,
    0.0,
    0.0,
    0.0,
    0.0,
    0.0,
    0.0,
    0.0,
    0.0,
    0.0,
    0.0,
    0.0,
    0.0,
    0.0,
    0.0,
    0.0,
    0.0,
    0.0,
    0.10907477385301152,
    0.0,
    0.0,
    0.0,
    0.0,
    0.0,
    0.0,
    0.0,
    0.0,
    0.0,
    0.0,
    0.0,
    0.0,
    0.0,
    0.0,
    0.0,
    0.0,
    0.0,
    0.0,
    0.0,
    0.0,
    0.0,
    0.0,
    0.0,
    0.0,
    0.0,
    0.0,
    0.0,
    0.0,
    0.0,
    0.0,
    0.0,
    0.0,
    0.0,
    0.0,
    0.0,
    0.0,
    0.0,
    0.0,
    0.0,
    0.0,
    0.0,
    0.0,
    0.05411888503348839,
    0.0,
    0.0,
    0.0,
    0.0,
    0.0,
    0.0,
    0.0,
    0.0,
    0.0,
    0.0,
    0.0,
    0.0,
    0.0,
    0.0709336219952718,
    0.0,
    0.0,
    0.0,
    0.0,
    0.0,
    0.0,
    0.0,
    0.0,
    0.0,
    0.0,
    0.0,
    0.0,
    0.0,
    0.0,
    0.0,
    0.0,
    0.1197266574896054,
    0.0,
    0.0,
    0.0,
    0.0,
    0.0,
    0.0,
    0.0,
    0.0,
    0.0,
    0.0,
    0.0,
    0.0,
    0.0,
    0.0,
    0.0,
    0.0,
    0.0,
    0.0,
    0.0,
    0.0,
    0.0,
    0.0,
    0.0,
    0.0,
    0.0,
    0.04620454950331966,
    0.0,
    0.06590120527568498,
    0.0,
    0.0,
    0.0,
    0.0,
    0.0,
    0.0,
    0.0,
    0.0,
    0.0,
    0.0,
    0.0,
    0.0,
    0.0,
    0.0,
    0.0,
    0.0,
    0.0,
    0.0,
    0.0,
    0.0,
    0.0,
    0.0,
    0.0,
    0.0,
    0.0,
    0.0,
    0.0,
    0.0,
    0.0,
    0.0,
    0.0,
    0.0,
    0.039442299658461924,
    0.0,
    0.0,
    0.0,
    0.0,
    0.0,
    0.0,
    0.0,
    0.0,
    0.0,
    0.0,
    0.0,
    0.0,
    0.04336925076296266,
    0.051147931546946156,
    0.0,
    0.04212645968749944,
    0.0,
    0.0,
    0.0,
    0.0,
    0.0,
    0.0,
    0.07088840879698456,
    0.0,
    0.0,
    0.0,
    0.0,
    0.0,
    0.0,
    0.0,
    0.0,
    0.0,
    0.0,
    0.0,
    0.0,
    0.0,
    0.0,
    0.0,
    0.0,
    0.0,
    0.0,
    0.0,
    0.0,
    0.0,
    0.0,
    0.0,
    0.0,
    0.0,
    0.04863846517240243,
    0.0,
    0.0,
    0.0,
    0.0,
    0.0,
    0.0,
    0.0,
    0.0,
    0.0,
    0.0,
    0.0,
    0.0,
    0.0,
    0.0,
    0.0,
    0.0,
    0.0,
    0.0,
    0.0,
    0.0,
    0.0,
    0.0,
    0.018564035514587296,
    0.0,
    0.0,
    0.0,
    0.06859036393389535,
    0.0,
    0.0,
    0.0,
    0.0,
    0.0,
    0.0,
    0.0,
    0.0,
    0.0,
    0.0,
    0.0,
    0.0,
    0.0,
    0.0,
    0.0,
    0.0,
    0.0,
    0.0,
    0.0,
    0.0,
    0.0,
    0.0,
    0.0,
    0.0,
    0.0,
    0.0,
    0.026771589990180682,
    0.0,
    0.0,
    0.0,
    0.0,
    0.0,
    0.0,
    0.0,
    0.0,
    0.0,
    0.0,
    0.0,
    0.0,
    0.0,
    0.0,
    0.0,
    0.0,
    0.0,
    0.0,
    0.0,
    0.0,
    0.0,
    0.0,
    0.0,
    0.0,
    0.0,
    0.0,
    0.0,
    0.0,
    0.0,
    0.0,
    0.0,
    0.0,
    0.0,
    0.0,
    0.041692963995909695,
    0.0,
    0.0,
    0.0,
    0.0,
    0.0,
    0.0,
    0.05141748587214646,
    0.05921275297369912,
    0.04684740466019808,
    0.04982367438124831,
    0.0,
    0.06752862096677616,
    0.08310975155177822,
    0.0,
    0.03890572742422247,
    0.04321085164612792,
    0.0,
    0.0,
    0.0,
    0.0,
    0.0,
    0.0,
    0.0,
    0.06739897824496979,
    0.1408490378390096,
    0.0,
    0.0,
    0.0,
    0.0,
    0.0,
    0.0,
    0.0,
    0.0,
    0.0,
    0.0,
    0.0,
    0.0,
    0.0,
    0.0,
    0.0,
    0.04139170952231258,
    0.0,
    0.0,
    0.0,
    0.0,
    0.0,
    0.08056993858489853,
    0.0,
    0.0,
    0.0,
    0.0,
    0.0,
    0.0,
    0.0,
    0.0,
    0.0,
    0.0,
    0.0,
    0.0,
    0.0,
    0.0,
    0.0,
    0.0,
    0.0,
    0.0,
    0.0,
    0.0,
    0.0,
    0.0,
    0.0,
    0.0,
    0.0,
    0.0,
    0.0,
    0.0,
    0.0,
    0.0,
    0.0,
    0.0,
    0.0,
    0.0,
    0.0,
    0.0,
    0.0,
    0.0,
    0.0,
    0.0,
    0.0,
    0.06930448443376858,
    0.0,
    0.0,
    0.0,
    0.0,
    0.0,
    0.0,
    0.0,
    0.0,
    0.0,
    0.0,
    0.0,
    0.0,
    0.0,
    0.0,
    0.08421198226803614,
    0.06234066422854138,
    0.0,
    0.0,
    0.0,
    0.0,
    0.0,
    0.0,
    0.0,
    0.0,
    0.0,
    0.0,
    0.0,
    0.0,
    0.0,
    0.07544443132807523,
    0.0,
    0.0,
    0.0,
    0.06130346837434386,
    0.0,
    0.0,
    0.0,
    0.0,
    0.0,
    0.0,
    0.0948588942860369,
    0.0,
    0.0,
    0.0,
    0.1123834562835906,
    0.0,
    0.0,
    0.0,
    0.0,
    0.0,
    0.0,
    0.0,
    0.13619701772186074,
    0.0,
    0.0,
    0.0,
    0.0,
    0.0,
    0.0,
    0.0,
    0.0,
    0.0,
    0.0,
    0.0,
    0.0,
    0.0,
    0.0,
    0.0,
    0.0,
    0.0,
    0.0,
    0.0,
    0.0,
    0.0,
    0.0,
    0.0,
    0.0,
    0.0,
    0.0,
    0.0,
    0.0,
    0.0,
    0.0,
    0.0,
    0.0,
    0.0,
    0.0,
    0.0,
    0.0,
    0.0,
    0.0,
    0.0,
    0.0,
    0.0,
    0.0,
    0.0,
    0.0,
    0.0,
    0.0,
    0.0,
    0.0,
    0.0,
    0.0,
    0.0,
    0.0,
    0.0,
    0.0,
    0.0,
    0.0,
    0.0,
    0.0,
    0.0,
    0.06910269110730964,
    0.0
  ],
  "vectorization_metadata": {
    "vectorizer_type": "TF-IDF",
    "vector_dimension": 3000,
    "processing_timestamp": "2025-12-13T16:05:26.587634"
  }
}